{
  "culture": "hu",
  "texts": {
    "Permissions": "Engedélyek",
    "Permission:OpenIddictPro": "OpenId",
    "Permission:Edit": "Szerkesztés",
    "Permission:Create": "Létrehozás",
    "Permission:Delete": "Törlés",
    "Permission:Application": "Alkalmazás",
    "Permission:ManagePermissions": "Engedélyek kezelése",
    "Permission:ViewChangeHistory": "Változástörténet megtekintése",
    "ChangeHistory": "Változástörténet",
    "Permission:Scope": "Hatókör",
    "InvalidRedirectUri": "Érvénytelen átirányítások: {0}",
    "InvalidPostLogoutRedirectUri": "Érvénytelen PostLogoutRedirectUri: {0}",
    "NoClientSecretCanBeSetForPublicApplications": "Nyilvános alkalmazásokhoz nem lehet beállítani ügyfél titkos kódot.",
    "TheClientSecretIsRequiredForConfidentialApplications": "A bizalmas alkalmazásokhoz szükség van az ügyfél titkos kódra.",
    "TheClientIdentifierIsAlreadyTakenByAnotherApplication": "Az ügyfélazonosítót már elfoglalta egy másik alkalmazás.",
    "TheScopeNameCannotContainSpaces": "A hatókör neve nem tartalmazhat szóközt",
    "TheNameIsAlreadyTakenByAnotherScope": "A nevet már átvette egy másik hatókör.",
    "Menu:OpenIddict": "OpenId",
    "Scopes": "Hatókör",
    "ScopeDeletionWarningMessage": "Biztosan törli a(z) '{0}' hatókört?",
    "Name": "Név",
    "DisplayName": "Megjelenítendő név",
    "Description": "Leírás",
    "Resources": "Erőforrások",
    "NewScope": "Új hatókör",
    "Applications": "Alkalmazások",
    "ApplicationDeletionWarningMessage": "Biztosan törli a(z) '{0}' alkalmazást?",
    "AreYouSure": "Biztos vagy ebben?",
    "NoAvailableScopes": "Nincs elérhető hatókör",
    "NewApplication": "Új alkalmazás",
    "ApplicationType": "Alkalmazás típusa",
    "ClientId": "Ügyfélazonosító",
    "ClientType": "Ügyfél típusa",
    "ClientSecret": "Ügyfél titkos kódja",
    "ClientSecretHelpText": "Adjon meg egy új értéket a meglévő titkosság helyére",
    "ClientUri": "Ügyfél Uri",
    "LogoUri": "Logo Uri",
    "AllowAuthorizationCodeFlow": "Engedélyezési kód áramlás engedélyezése",
    "AllowImplicitFlow": "Implicit Flow engedélyezése",
    "AllowPasswordFlow": "Jelszófolyam engedélyezése",
    "AllowClientCredentialsFlow": "Ügyfél hitelesítő adatainak áramlásának engedélyezése",
    "AllowHybridFlow": "Hibrid áramlás engedélyezése",
    "AllowRefreshTokenFlow": "Token Flow frissítésének engedélyezése",
    "AllowDeviceEndpoint": "Eszközvégpont engedélyezése",
    "AllowLogoutEndpoint": "Kijelentkezési végpont engedélyezése",
    "ExtensionGrantTypes": "Kiterjesztési engedélytípusok",
    "RedirectUris": "Uri-k átirányítása",
    "PostLogoutRedirectUris": "Kijelentkezés utáni átirányítási Uri-k",
    "ConsentType": "Hozzájárulás típusa",
    "NotAvailableForThisType": "Ennél a típusnál nem elérhető",
    "TokenLifetime": "Token élettartama",
    "TokenLifetimeHit": "A token élettartamának mértékegysége másodperc, üresen hagyva az alapértelmezett élettartam használatához.",
    "AccessTokenLifetime": "AccessToken élettartama",
    "AuthorizationCodeLifetime": "AuthorizationCode élettartama",
    "DeviceCodeLifetime": "DeviceCode élettartama",
    "IdentityTokenLifetime": "IdentityToken élettartama",
    "RefreshTokenLifetime": "RefreshToken élettartama",
    "UserCodeLifetime": "UserCode élettartama"
  }
}
