{
  "culture": "es",
  "texts": {
    "Forms:0001": "Ya proporcionas respuesta.",
    "Forms:0002": "Debe proporcionar una dirección de correo electrónico.",
    "Forms:0003": "No puede editar su respuesta.",
    "Permission:Forms": "Formulario",
    "Permission:Forms.Management": "Administración de formulario",
    "Permission:Forms.Response.Management": "Gestión de respuesta",
    "Permission:Forms:Response.Delete": "Eliminando respuesta",
    "Feature:FormsGroup": "Formularios",
    "Feature:FormsEnable": "Habilitar formularios",
    "Feature:FormsEnableDescription": "Habilite el sistema de formularios en la aplicación.",
    "Menu:Forms": "Formularios",
    "Menu:Questions": "Preguntas",
    "Menu:Responses": "Respuestas",
    "Menu:Settings": "Ajustes",
    "Menu:Send": "Enviar",
    "Menu:Forms.Management": "Administración de formularios",
    "Menu:Forms.Responded": "Formularios respondidos",
    "Menu:NewForm": "Crear nuevo formulario",
    "FormDeletionConfirmationMessage": "El formulario sera eliminado y todas su preguntas con este, confirma la eliminacion?",
    "Form:TitleRequired": "El título es obligatorio",
    "Form:IsNotAcceptingResponses": "La forma ya no acepta respuestas.",
    "Form:SendFormInvitation": "Te he invitado a rellenar un formulario:",
    "Form:SendFormHeader": "Enviar formulario",
    "Form:SendFormCopiedToClipboard": "Copiado al portapapeles.",
    "Form:Submit": "Enviar",
    "Form:Update": "Actualizar",
    "FormSettings:Edit": "Editar configuración de formulario",
    "FormSettings:IsAcceptingResponses": "Está aceptando respuestas",
    "FormSettings:IsCollectingEmail": "Está recopilando correo electrónico",
    "FormSettings:IsQuiz": "Es una prueba",
    "FormSettings:RequiresLogin": "Requiere inicio de sesión",
    "FormSettings:HasLimitOneResponsePerUser": "Tiene limite de una respuesta por usuario",
    "FormSettings:CanEditResponse": "Puede edutar despues de enviar",
    "FormSettings:Form": "Formulario",
    "FormSettings:FormIs": "El formulario es",
    "Form:Questions:Settings": "Ajustes",
    "Form:Questions:NewQuestion": "Nueva pregunta",
    "Form:Questions:Preview": "Avance",
    "Form:Questions:Required": "Requerido",
    "Form:Questions:Save": "Ahorrar",
    "Form:Questions:Remove": "Eliminar",
    "Form:Questions:QuestionIndex": "Pregunta {0}",
    "Form:Questions:ModifiedAt": "Modificado en {0}",
    "Form:Responses:TotalResponses": "{0} respuestas",
    "Form:Responses:NoResponse": "Aún no hay respuesta",
    "Form:Responses:BlankQuestion": "Pregunta dejada en blanco",
    "Form:Responses:DownloadResponses": "Descargar respuestas (.csv)",
    "Form:Responses:DeleteResponse": "Eliminar respuesta",
    "Form:Responses:PrintResponse": "Imprimir respuesta",
    "Form:Responses:PreviousResponse": "Respuesta anterior",
    "Form:Responses:NextResponse": "Siguiente respuesta",
    "Form:Responses:DeleteAllResponses": "Eliminar todas las respuestas",
    "Form:Responses:AcceptingResponses": "Aceptando respuestas",
    "Form:Responses:NotAcceptingResponses": "No aceptar respuestas",
    "Form:Responses:ResponseWillBeDeletedMsg": "Esta respuesta será eliminada",
    "Form:Responses:AllResponsesWillBeDeletedMsg": "Todas las respuestas serán eliminadas",
    "FormSettings:Respondents": "Encuestados",
    "Answer:RequiredQuestion": "Esta es una pregunta requerida",
    "Answer:RequiredField": "Este es un campo requerido",
    "Answer:AnswerPlaceholder": "Su respuesta",
    "Choice:Remove": "Eliminar",
    "Choice:AddOption": "Agregar opción",
    "Choice:Or": "o",
    "Choice:AddOther": "Añadir otro\"",
    "Choice:Other": "Otro...",
    "Choice:Option": "Opción",
    "QuestionType:ShortText": "Respuesta corta",
    "QuestionType:ChoiceMultiple": "Opción multiple",
    "QuestionType:Checkbox": "Casilla de verificación",
    "QuestionType:DropdownList": "Desplegable",
    "ViewForm:EnterPropertyDesc": "Ingrese su {0}",
    "ViewForm:InvalidPropertyError": "Ingrese un {0} válido",
    "ViewForm:PropertyPlaceholder": "Tu {0}",
    "ViewForm:NotFound": "Formulario no encontrado",
    "ViewForm:NotFoundDescription": "No se pudo encontrar el formulario que está intentando ver. Puede no existir o puede ser privado para diferentes usuarios inquilinos. Por favor contacte con el administrador del formulario.",
    "Response:SavedResponse": "Su respuesta ha sido registrada.",
    "Response:SubmitNewAnswer": "Enviar nueva respuesta",
    "Response:EditYourResponse": "Edita tu respuesta",
    "Response:EditingResponseMsg": "Estás editando tu respuesta.",
    "DeletedSuccessfully": "Borrado exitosamente",
    "View": "Vista",
    "Title": "Título",
    "Description": "Descripción",
    "UpdatedAt": "Actualizado en",
    "CreatedAt": "Creado en",
    "Email": "Correo electrónico",
    "Link": "Enlace",
    "To": "Para",
    "Subject": "Tema",
    "Body": "Cuerpo",
    "Close": "Cerrar",
    "Send": "Enviar",
    "Copy": "Dupdo",
    "Individual": "Individual",
    "GoToHomePage": "Ir a la pagina principal",
    "GoBack": "Regresa"
  }
}