{
  "culture": "tr",
  "texts": {
    "Actions": "İşlemler",
    "AndUnderstandThatICanUnsubscribeAtAnyTime": "ve istediğim zaman abonelikten çıkabileceğimi anlıyorum.",
    "BlogDeletionConfirmationMessage": "'{0}' adlı blog silinecek. Emin misiniz?",
    "BlogFeatureNotAvailable": "Bu özellik kullanılabilir değil. 'GlobalFeatureManager' ile aktif ederek kullanabilisiniz.",
    "BlogId": "Blog",
    "BlogPostDeletionConfirmationMessage": "'{0}' başlıklı blog yazısı silinecek. Emin misiniz?",
    "BlogPosts": "Blog Yazıları",
    "Blogs": "Bloglar",
    "ChoosePreference": "Tercih seçiniz...",
    "Cms": "CMS",
    "CmsKit.Comments": "Yorumlar",
    "CmsKit.Ratings": "Puanlama",
    "CmsKit.Reactions": "Tepkiler",
    "CmsKit.Tags": "Etiketler",
    "CommentDeletionConfirmationMessage": "Bu yorum ve buna yapılan tüm yorumlan silinecektir!",
    "Comments": "Yorumlar",
    "ContactSuccess": "Mesajınız başarılı bir şekilde gönderilmiştir.",
    "ContentDeletionConfirmationMessage": "Bu içeriği gerçekten silmek istediğinize emin misiniz?",
    "Contents": "İçerikler",
    "CoverImage": "Kapak Resmi",
    "CreateBlogPostPage": "Yeni Blog Yazısı",
    "CreationTime": "Oluşturulma Zamanı",
    "Detail": "Detay",
    "Details": "Detaylar",
    "DoYouPreferAdditionalEmails": "Ek e-postaları tercih ediyor musunuz?",
    "Edit": "Düzenle",
    "EmailAddress": "E-mail Adresi",
    "EmailAddressPermissionManagement": "E-posta adresiniz (\"{0}\") ile birlikte , aşağıdaki izinleri vermiş olursunuz.",
    "EmailToException": "Mesajın gönderileceği e-posta adresini belirtmeniz gerekmektedir.",
    "EndDate": "Bitiş Tarihi",
    "EntityId": "Entity Id",
    "EntityType": "Entity Tür",
    "ExportCSV": "CSV olarak dışa aktar",
    "Features": "Özellikler",
    "GenericDeletionConfirmationMessage": "'{0}' kaydını silmek istediğinize emin misiniz?",
    "GetDealsAndSpecialOffersForThe": "\"{0}\" için fırsatlar ve özel teklifler alın",
    "HowMayWeHelpYou": "Size nasıl yardımcı olabiliriz?",
    "IHaveReadThe": "Okudum",
    "Message": "Mesaj",
    "Name": "Ad",
    "New": "Yeni",
    "NewsletterEmailFooterTemplateDeleteSubscription": "<small> Eğer bu işlemi yanlışlıkla yaptıysanız, aboneliğinizi <a href=\"{0}\">{1}</a></small> adresini ziyaret ederek tekrar aktive edebilirsiniz.",
    "NewsletterEmailFooterTemplateManageEmail": "<a href=\"{0}\">E-posta tercihlerinizi buradan yönetebilirsiniz.</a>",
    "NewsletterDeleteSubscriptionMessage": "Artık \"{0}\" adresinize otomatik e-postalar göndermeyeceğiz.",
    "NewsletterDeleteSubscriptionSubject": "Abonelik iptal edildi.",
    "NewsletterDeleteSubscriptionDescription": "{0} bülten abonelikleriniz sonlandırılmıştır",
    "NewsletterEmailFooterCreateTemplateMessage": "E-posta tercihleriniz başarıyla kaydedilmiştir.",
    "NewsletterEmailFooterTemplateTitle": "Bültenimize abone olduğunuz için bu mesajı almaktasınız.",
    "NewsletterEmailFooterUpdateTemplateMessage": "E-posta tercihleriniz başarıyla güncellenmiştir.",
    "NewsletterEmailMessage": "Bizi seçtiğiniz için mutluyuz.",
    "NewsletterEmailSubject": "Bültene abone oldum",
    "NewsletterEmailTitle": "Abone olduğunuz için teşekkürler!",
    "NewsletterUsers": "Bülten Kullanıcıları",
    "NewsletterSuccessMessage": "Teşekkürler",
    "NewsletterUpdatePreferenceMessage": "Tercihleriniz başarıyla değiştirildi.",
    "NewsletterUpdatePreferenceTitle": "E-posta Tercihleriniz",
    "NewsletterUpdatePreferenceTitleSubject": "Abonelik tercihleriniz güncellendi",
    "OK": "Tamam",
    "PageDeletionConfirmationMessage": "Bu sayfayı silmek istediğinize emin misiniz?",
    "PageSlugInformation": "Etiket URL'de kullanılır. Url şöyle görünür: '/pages/{{slug}}'.",
    "Permission:BlogManagement": "Blog Yönetimi",
    "Permission:BlogManagement.Create": "Oluşturma",
    "Permission:BlogManagement.Delete": "Silme",
    "Permission:BlogManagement.Update": "Güncelleme",
    "Permission:BlogPostManagement": "Blog Yazıları Yönetimi",
    "Permission:BlogPostManagement.Create": "Oluşturma",
    "Permission:BlogPostManagement.Delete": "Silme",
    "Permission:BlogPostManagement.Update": "Güncelleme",
    "Permission:NewsletterManagement": "Bülten Yönetimi",
    "Permission:Contact:SettingManagement": "İletişim Ayar Yönetimi",
    "Permission:UrlShorting": "URL Kısaltma",
    "Permission:UrlShorting.Create": "Yeni kısaltılmış url oluştur",
    "Permission:UrlShorting.Update": "Kısaltılmış url'i güncelle",
    "Permission:UrlShorting.Delete": "Kısaltılmış url'i sil",
    "Preference": "Tercih",
    "PrivacyPolicy": "Gizlilik Politikasını",
    "RepliesToThisComment": "Bu yoruma yapılan yorumlar",
    "ReplyTo": "Cevap",
    "SamplePageMessage": "Pro modulünden örnek bir sayfa",
    "SaveChanges": "Değişiklikleri Kaydet",
    "SelectAll": "Hepsini seç",
    "SendMessage": "Mesajı Gönder",
    "ShortDescription": "Kısa açıklama",
    "Slug": "Etiket",
    "Source": "Kaynak",
    "SourceUrl": "Kaynak Link",
    "StartDate": "Başlangıç Tarihi",
    "Subject": "Konu",
    "SubjectPlaceholder": "Lütfen bir konu yazınız",
    "Submit": "Kaydet",
    "Subscribe": "Abone ol",
    "SuccessfullyDeleted": "Başarıyla silindi!",
    "SavedSuccessfully": "Başarıyla kaydedildi!",
    "Text": "Metin",
    "ThankYou": "Teşekkürler",
    "Title": "Başlık",
    "UpdatePreferenceSuccessMessage": "Tercihleriniz kaydedilmiştir.",
    "UpdateYourEmailPreferences": "E-posta tercihlerinizi güncelleyin",
    "UploadFailedMessage": "Karşıya yükleme işlemi başarısız oldu.",
    "UserId": "Kullanıcı Id",
    "Username": "Kullanıcı adı",
    "YourEmailAddress": "Email adresiniz",
    "YourFullName": "Tam adınız",
    "YourMessage": "Mesajınız",
    "Settings:Menu:CmsKit": "CMS",
    "ReceiverEmailAddress": "Alıcı Eposta Adresi",
    "CmsKitPro:Contact": "İletişim",
    "ForwardedUrlDeletionConfirmationMessage": "Bu URL'i silmek istediğinize emin misiniz?",
    "Target": "Hedef",
    "ForwardaUrl": "Bir URL yönlendir",
    "UrlForwarding": "URL yönlendirme",
    "CmsKitPro:UrlForwarding:0001": "Bu URL zaten kullanımda. ({Source})",
    "UrlForwarding:EnsureTheUrlIsStartingWithSlash": "URL'in ileri slash (\"/\") ile başladığına emin olun",
    "UrlForwarding:EnsureTheUrlIsStartingWithSlashIfSameDomain": "Aynı domain'i hedef alıyorsa, URL ileri slash (\"/\") ile başlamalı",
    "Permission:Poll": "Poll Yönetimi",
    "Permission:Poll.Create": "Oluşturma",
    "Permission:Poll.Update": "Güncelleme",
    "Permission:Poll.Delete": "Silme",
    "Polls": "Anketler",
    "PollDeletionConfirmationMessage": "Bu içeriği gerçekten silmek istediğinize emin misiniz?",
    "ChooseOneOption": "Bir seçim yapbilirsiniz",
    "ChooseOneOrMoreOption": "Bir veya birden fazla seçim yapabilirsiniz",
    "YouHaventSelectedAnyOption": "En az bir seçim yapmalısınız!",
    "Vote": "Oy Ver",
    "VoteCount": "Oy sayısı",
    "VoteCount{0}": "{0} oy",
    "NoVotes": "Oy yok",
    "SingleVoteCount": "1 oy",
    "Results": "Sonuçlar",
    "ReturnVoting": "Oylamaya dön",
    "FinalResult": "Sonuç",
    "TimeLeft": "{0} saat kaldı",
    "MonthsLeft": "{0} ay kaldı",
    "MonthLeft": "{0} ay kaldı",
    "DaysLeft": "{0} gün kaldı",
    "DayLeft": "{0} gün kaldı",
    "HoursLeft": "{0} saat kaldı",
    "HourLeft": "{0} saat kaldı",
    "MinutesLeft": "{0} dakika kaldı",
    "MinuteLeft": "{0} dakika kaldı",
    "SecondsLeft": "{0} saniye kaldı",
    "SecondLeft": "{0} saniye kaldı",
    "CmsKitPro:Poll:0001": "Anket bir seçime izin vermektedir {AllowMultipleVote}",
    "CmsKitPro:Poll:0002": "Bitiş tarihi başlangıç tarihinden büyük olamaz {StartDate} {EndDate}",
    "CmsKitPro:Poll:0003": "Gösterim tarihi başlangıç tarihinden büyük olamaz {StartDate} {ResultShowingEndDate}",
    "CmsKitPro:Poll:0004": "Aynı kullanıcı bir kere oy verebilir",
    "CmsKitPro:Poll:0005": "Widget ismi aynı olamaz {Widget}",
    "CmsKitPro:Poll:0006": "Aynı ismide Widget var: {Name}",
    "CmsKitPro:Poll:0007": "Oops, bir hata meydana geldi. Lütfen daha sonra tekrar deneyin.",
    "Question": "Soru",
    "AllowMultipleVote": "Çoklu Oy Verilsin",
    "ShowVoteCount": "Toplam Oyu Göster",
    "ShowHoursLeft": "Kalan Süreyi Göster",
    "Options": "Seçenekler",
    "AddNew": "Yeni Ekle",
    "NewPoll": "Yeni Anket",
    "Widget": "Araç",
    "NewOption": "Yeni Seçenek",
    "LoginToVote": "Giriş Yapın",
    "Poll:NameJustForMoreReadable": "İsim komponent içerisinde kullanılmaz. Sadece daha okunaklı olması içindir",
    "Poll:CodeUsedToChooseWidget": "Code anketi seçmek için kullanılır",
    "Poll:YouShouldCreateAtLeastTwoOptions": "En az 2 seçenek oluşturmalısınız",
    "ShowResults": "Sonuçları Göster",
    "Close": "Kapat",
    "CopyWidgetCode": "Widget Kodu Kopyala",
    "CopiedWidgetCode": "Widget Kodu Kopyalandı",
    "CouldntFindWidgetWith": "Böyle bir widget bulunmadı",
    "Feature:CmsKitProGroup": "Cms Kit Pro",
    "Feature:ContactEnable": "İletişim",
    "Feature:ContactEnableDescription": "Cmskit iletişim sistemi",
    "Feature:NewsletterEnable": "Bülten",
    "Feature:NewsletterEnableDescription": "Cmskit bülten sistemi",
    "Feature:PollEnable": "Anket",
    "Feature:PollEnableDescription": "Cmskit anket sistemi",
    "Feature:UrlShortingEnable": "Url yönlendirme",
    "Feature:UrlShortingEnableDescription": "Cmskit url yönlendirme sistemi",
    "CmsKitPro:PageFeedback:0001": "{EntityType} varlığı geri bildirimde bulunamıyor",
    "IsHandled": "İşleniyor",
    "IsUseful": "Kullanışlı",
    "UserNote": "Kullanıcı Notu",
    "AdminNote": "Yönetici Notu",
    "Url": "URL",
    "Permission:PageFeedback": "Sayfa Geri Bildirim Yönetimi",
    "Permission:PageFeedback.Update": "Sayfa geri bildirimini güncelleme",
    "Permission:PageFeedback.Delete": "Sayfa geri bildirimini silme",
    "Permission:PageFeedback.Settings": "Sayfa Geri Bildirimi Ayarları Yönetimi",
    "PageFeedbacks": "Sayfa Geri Bildirimleri",
    "PageFeedbackDeletionConfirmationMessage": "Bu sayfa geri bildirimini sildiğinizden emin misiniz?",
    "Feature:PageFeedbackEnable": "Sayfa Geri Bildirimi",
    "Feature:PageFeedbackEnableDescription": "CMS Kit&#39;in, kullanıcıların belirli bir sayfa hakkında geri bildirim göndermesine olanak tanıyan sayfa geri bildirim sistemi.",
    "PageFeedbackInputPlaceholder": "Deneyiminizi bizimle paylaşın ancak lütfen hassas veya kişisel bilgilerinizi eklemeyin.",
    "PageFeedbackValidationError": "Lütfen bir seçim yapın.",
    "PageFeedback:ThankYouTitle": "Değerli geri bildiriminiz için teşekkür ederiz!",
    "PageFeedback:ThankYouDescription": "Geri bildirimlere yanıt veremesek de ekibimizin yorumlarınızı deneyimi geliştirmek için kullanacağını lütfen unutmayın.",
    "PageFeedback:Header": "Bu sayfa faydalı oldu mu?",
    "PageFeedback": "Sayfa Geri Bildirimi",
    "FallBackEmailAddressInfo": "Varlık türüne herhangi bir e-posta adresi atanmamışsa bu e-posta adresi kullanılacaktır.",
    "PageFeedback:Settings:EmailAddresses:Placeholder": "notify1@mail.com, notify2@mail.com",
    "EmailAddresses": "E-mail adresleri",
    "EmailAddresses:Info": "Yeni bir geri bildirim oluşturulduğunda bilgilendirilecek e-posta adresleri. Birden fazla e-posta adresini virgülle ayırarak girebilirsiniz.",
    "MultipleEmailsValidationError": "Lütfen &quot;{0}&quot; için geçerli bir e-posta adresi girin",
    "MailSettings": "Posta Ayarları",
    "InvalidEmailAddress": "{0} e-posta adresi geçerli değil!",
    "HeaderText": "Başlık metni",
    "YesButtonText": "Evet Düğme Metni",
    "NoButtonText": "Düğme Metni Yok",
    "ReverseButtons": "Ters Düğmeler",
    "SubmitButtonText": "Gönder Düğmesi Metni",
    "UserNotePlaceholder": "Kullanıcı Notu Yer Tutucusu",
    "ThankYouMessageTitle": "Teşekkür Mesajı Başlığı",
    "ThankYouMessageDescription": "Teşekkür Mesajı Açıklaması",
    "HeaderVisible": "başlığı göster",
    "EmailPreferences": "E-mail tercihleri",
    "UserDoesNotHaveAnyNewsletterSubscription": "Şu anda sistemimizde abone olduğunuz bir bülten bulunmamaktadır. E-posta tercihleriniz güncel ve şu anda bizden herhangi bir haber bülteni almıyorsunuz.",
    "ManageEmailPreferencesForSubscribedNewsletters": "Gelecekte haber bültenlerimizi keşfetmek isterseniz uygulamamız üzerinden kolayca abone olabilir ve e-posta tercihlerinizi bu sayfadan yönetebilirsiniz.",
    "PollWithSameDateRangeAndWidgetAlreadyExists": "Aynı tarih aralığına ve widget'a sahip anket zaten mevcut. Anket Kodu: {0}",
    "VotedSuccessfully": "Başarıyla oy verildi!",
    "ResultShowingEndDate": "Son Gösterim Tarihi",
    "ShowResultWithoutGivingVote": "Oy Vermeden Sonucu Görüntüle",
    "Poll:CodeIsAUniqueKey": "Kod, sistem tarafından oluşturulan benzersiz bir anahtardır ve değiştirilemez",
    "Poll:NameIsUsedToFilterInAdminSide": "Ad, yönetici tarafında bu anketi filtrelemek için kullanılır. Anket bölümüne yazdırılmaz.",
    "PleaseSelectABlog": "Lütfen bir blog seçin",
    "SubscribeWithEmail": "E-posta adresiyle bültene abone olun ",
    "SubscribeToNewsletter": "Bültene abone olun",
    "Order": "Sıra",
    "GroupName": "Grup Adı",
    "QuestionCount": "Soru Sayısı",
    "AddNewQuestion": "Yeni soru ekle",
    "QuestionText": "Soru metni",
    "Preview": "Ön İzleme",
    "CreateFaq": "SSS bölümü oluştur",
    "EditFaq": "SSS bölümü günclle",
    "EditQuestion": "Soru güncelle",
    "Faqs": "SSS",
    "NewFaq": "Yeni SSS bölümü",
    "Permission:Faq": "SSS",
    "Permission:Faq.Create": "SSS oluştur",
    "Permission:Faq.Update": "SSS güncelle",
    "Permission:Faq.Delete": "SSS sil",
    "Feature:FaqEnable": "SSS",
    "Feature:FaqEnableDescription": "CMS Kit SSS sistemi",
    "FaqDeletionConfirmationMessage": "'{0}' adlı SSS silinecek. Emin misiniz?",
    "NullFaqData": " '{0}' grup adında '{1}' isimli veri bulunamadı!",
    "MarkdownSupported": "Markdown destekleniyor",
    "CmsKitPro:FaqSection:0001": "SSS bölümü zaten var. {GroupName} {Name}",
    "CmsKitPro:FaqSection:0002": "Geçersiz grup adı {GroupName}",
    "CmsKitPro:FaqQuestion:0001": "SSS sorusu zaten var. {Title} {Text}",
    "NewQuestion": "Yeni Soru"
  }
}